{
  "frames": {
    "town_center_foundation":     {"frame":{"x":0,"y":0,"w":192,"h":160},"anchor":{"x":96,"y":140}},
    "town_center_construction_1": {"frame":{"x":0,"y":0,"w":192,"h":160},"anchor":{"x":96,"y":140}},
    "town_center_construction_2": {"frame":{"x":0,"y":0,"w":192,"h":160},"anchor":{"x":96,"y":140}},
    "town_center_construction_3": {"frame":{"x":0,"y":0,"w":192,"h":160},"anchor":{"x":96,"y":140}},
    "town_center_complete":       {"frame":{"x":0,"y":0,"w":192,"h":160},"anchor":{"x":96,"y":140}},
    "town_center_fire":           {"frame":{"x":0,"y":0,"w":192,"h":160},"anchor":{"x":96,"y":140}},

    "house_foundation":     {"frame":{"x":0,"y":0,"w":96,"h":80},"anchor":{"x":48,"y":72}},
    "house_construction_1": {"frame":{"x":0,"y":0,"w":96,"h":80},"anchor":{"x":48,"y":72}},
    "house_construction_2": {"frame":{"x":0,"y":0,"w":96,"h":80},"anchor":{"x":48,"y":72}},
    "house_construction_3": {"frame":{"x":0,"y":0,"w":96,"h":80},"anchor":{"x":48,"y":72}},
    "house_complete":       {"frame":{"x":0,"y":0,"w":96,"h":80},"anchor":{"x":48,"y":72}},
    "house_fire":           {"frame":{"x":0,"y":0,"w":96,"h":80},"anchor":{"x":48,"y":72}},

    "barracks_foundation":     {"frame":{"x":0,"y":0,"w":144,"h":120},"anchor":{"x":72,"y":108}},
    "barracks_construction_1": {"frame":{"x":0,"y":0,"w":144,"h":120},"anchor":{"x":72,"y":108}},
    "barracks_construction_2": {"frame":{"x":0,"y":0,"w":144,"h":120},"anchor":{"x":72,"y":108}},
    "barracks_construction_3": {"frame":{"x":0,"y":0,"w":144,"h":120},"anchor":{"x":72,"y":108}},
    "barracks_complete":       {"frame":{"x":0,"y":0,"w":144,"h":120},"anchor":{"x":72,"y":108}},
    "barracks_fire":           {"frame":{"x":0,"y":0,"w":144,"h":120},"anchor":{"x":72,"y":108}},

    "archery_range_foundation":     {"frame":{"x":0,"y":0,"w":144,"h":120},"anchor":{"x":72,"y":108}},
    "archery_range_construction_1": {"frame":{"x":0,"y":0,"w":144,"h":120},"anchor":{"x":72,"y":108}},
    "archery_range_construction_2": {"frame":{"x":0,"y":0,"w":144,"h":120},"anchor":{"x":72,"y":108}},
    "archery_range_construction_3": {"frame":{"x":0,"y":0,"w":144,"h":120},"anchor":{"x":72,"y":108}},
    "archery_range_complete":       {"frame":{"x":0,"y":0,"w":144,"h":120},"anchor":{"x":72,"y":108}},
    "archery_range_fire":           {"frame":{"x":0,"y":0,"w":144,"h":120},"anchor":{"x":72,"y":108}},

    "stable_foundation":     {"frame":{"x":0,"y":0,"w":144,"h":120},"anchor":{"x":72,"y":108}},
    "stable_construction_1": {"frame":{"x":0,"y":0,"w":144,"h":120},"anchor":{"x":72,"y":108}},
    "stable_construction_2": {"frame":{"x":0,"y":0,"w":144,"h":120},"anchor":{"x":72,"y":108}},
    "stable_construction_3": {"frame":{"x":0,"y":0,"w":144,"h":120},"anchor":{"x":72,"y":108}},
    "stable_complete":       {"frame":{"x":0,"y":0,"w":144,"h":120},"anchor":{"x":72,"y":108}},
    "stable_fire":           {"frame":{"x":0,"y":0,"w":144,"h":120},"anchor":{"x":72,"y":108}},

    "siege_workshop_foundation":     {"frame":{"x":0,"y":0,"w":144,"h":120},"anchor":{"x":72,"y":108}},
    "siege_workshop_construction_1": {"frame":{"x":0,"y":0,"w":144,"h":120},"anchor":{"x":72,"y":108}},
    "siege_workshop_construction_2": {"frame":{"x":0,"y":0,"w":144,"h":120},"anchor":{"x":72,"y":108}},
    "siege_workshop_construction_3": {"frame":{"x":0,"y":0,"w":144,"h":120},"anchor":{"x":72,"y":108}},
    "siege_workshop_complete":       {"frame":{"x":0,"y":0,"w":144,"h":120},"anchor":{"x":72,"y":108}},
    "siege_workshop_fire":           {"frame":{"x":0,"y":0,"w":144,"h":120},"anchor":{"x":72,"y":108}},

    "blacksmith_foundation":     {"frame":{"x":0,"y":0,"w":144,"h":120},"anchor":{"x":72,"y":108}},
    "blacksmith_construction_1": {"frame":{"x":0,"y":0,"w":144,"h":120},"anchor":{"x":72,"y":108}},
    "blacksmith_construction_2": {"frame":{"x":0,"y":0,"w":144,"h":120},"anchor":{"x":72,"y":108}},
    "blacksmith_construction_3": {"frame":{"x":0,"y":0,"w":144,"h":120},"anchor":{"x":72,"y":108}},
    "blacksmith_complete":       {"frame":{"x":0,"y":0,"w":144,"h":120},"anchor":{"x":72,"y":108}},
    "blacksmith_fire":           {"frame":{"x":0,"y":0,"w":144,"h":120},"anchor":{"x":72,"y":108}},

    "market_foundation":     {"frame":{"x":0,"y":0,"w":144,"h":120},"anchor":{"x":72,"y":108}},
    "market_construction_1": {"frame":{"x":0,"y":0,"w":144,"h":120},"anchor":{"x":72,"y":108}},
    "market_construction_2": {"frame":{"x":0,"y":0,"w":144,"h":120},"anchor":{"x":72,"y":108}},
    "market_construction_3": {"frame":{"x":0,"y":0,"w":144,"h":120},"anchor":{"x":72,"y":108}},
    "market_complete":       {"frame":{"x":0,"y":0,"w":144,"h":120},"anchor":{"x":72,"y":108}},
    "market_fire":           {"frame":{"x":0,"y":0,"w":144,"h":120},"anchor":{"x":72,"y":108}},

    "monastery_foundation":     {"frame":{"x":0,"y":0,"w":144,"h":120},"anchor":{"x":72,"y":108}},
    "monastery_construction_1": {"frame":{"x":0,"y":0,"w":144,"h":120},"anchor":{"x":72,"y":108}},
    "monastery_construction_2": {"frame":{"x":0,"y":0,"w":144,"h":120},"anchor":{"x":72,"y":108}},
    "monastery_construction_3": {"frame":{"x":0,"y":0,"w":144,"h":120},"anchor":{"x":72,"y":108}},
    "monastery_complete":       {"frame":{"x":0,"y":0,"w":144,"h":120},"anchor":{"x":72,"y":108}},
    "monastery_fire":           {"frame":{"x":0,"y":0,"w":144,"h":120},"anchor":{"x":72,"y":108}},

    "university_foundation":     {"frame":{"x":0,"y":0,"w":144,"h":120},"anchor":{"x":72,"y":108}},
    "university_construction_1": {"frame":{"x":0,"y":0,"w":144,"h":120},"anchor":{"x":72,"y":108}},
    "university_construction_2": {"frame":{"x":0,"y":0,"w":144,"h":120},"anchor":{"x":72,"y":108}},
    "university_construction_3": {"frame":{"x":0,"y":0,"w":144,"h":120},"anchor":{"x":72,"y":108}},
    "university_complete":       {"frame":{"x":0,"y":0,"w":144,"h":120},"anchor":{"x":72,"y":108}},
    "university_fire":           {"frame":{"x":0,"y":0,"w":144,"h":120},"anchor":{"x":72,"y":108}},

    "castle_foundation":     {"frame":{"x":0,"y":0,"w":192,"h":160},"anchor":{"x":96,"y":140}},
    "castle_construction_1": {"frame":{"x":0,"y":0,"w":192,"h":160},"anchor":{"x":96,"y":140}},
    "castle_construction_2": {"frame":{"x":0,"y":0,"w":192,"h":160},"anchor":{"x":96,"y":140}},
    "castle_construction_3": {"frame":{"x":0,"y":0,"w":192,"h":160},"anchor":{"x":96,"y":140}},
    "castle_complete":       {"frame":{"x":0,"y":0,"w":192,"h":160},"anchor":{"x":96,"y":140}},
    "castle_fire":           {"frame":{"x":0,"y":0,"w":192,"h":160},"anchor":{"x":96,"y":140}},

    "dock_foundation":     {"frame":{"x":0,"y":0,"w":144,"h":120},"anchor":{"x":72,"y":108}},
    "dock_construction_1": {"frame":{"x":0,"y":0,"w":144,"h":120},"anchor":{"x":72,"y":108}},
    "dock_construction_2": {"frame":{"x":0,"y":0,"w":144,"h":120},"anchor":{"x":72,"y":108}},
    "dock_construction_3": {"frame":{"x":0,"y":0,"w":144,"h":120},"anchor":{"x":72,"y":108}},
    "dock_complete":       {"frame":{"x":0,"y":0,"w":144,"h":120},"anchor":{"x":72,"y":108}},
    "dock_fire":           {"frame":{"x":0,"y":0,"w":144,"h":120},"anchor":{"x":72,"y":108}},

    "lumber_camp_foundation":     {"frame":{"x":0,"y":0,"w":96,"h":80},"anchor":{"x":48,"y":72}},
    "lumber_camp_construction_1": {"frame":{"x":0,"y":0,"w":96,"h":80},"anchor":{"x":48,"y":72}},
    "lumber_camp_construction_2": {"frame":{"x":0,"y":0,"w":96,"h":80},"anchor":{"x":48,"y":72}},
    "lumber_camp_construction_3": {"frame":{"x":0,"y":0,"w":96,"h":80},"anchor":{"x":48,"y":72}},
    "lumber_camp_complete":       {"frame":{"x":0,"y":0,"w":96,"h":80},"anchor":{"x":48,"y":72}},
    "lumber_camp_fire":           {"frame":{"x":0,"y":0,"w":96,"h":80},"anchor":{"x":48,"y":72}},

    "mining_camp_foundation":     {"frame":{"x":0,"y":0,"w":96,"h":80},"anchor":{"x":48,"y":72}},
    "mining_camp_construction_1": {"frame":{"x":0,"y":0,"w":96,"h":80},"anchor":{"x":48,"y":72}},
    "mining_camp_construction_2": {"frame":{"x":0,"y":0,"w":96,"h":80},"anchor":{"x":48,"y":72}},
    "mining_camp_construction_3": {"frame":{"x":0,"y":0,"w":96,"h":80},"anchor":{"x":48,"y":72}},
    "mining_camp_complete":       {"frame":{"x":0,"y":0,"w":96,"h":80},"anchor":{"x":48,"y":72}},
    "mining_camp_fire":           {"frame":{"x":0,"y":0,"w":96,"h":80},"anchor":{"x":48,"y":72}},

    "mill_foundation":     {"frame":{"x":0,"y":0,"w":96,"h":80},"anchor":{"x":48,"y":72}},
    "mill_construction_1": {"frame":{"x":0,"y":0,"w":96,"h":80},"anchor":{"x":48,"y":72}},
    "mill_construction_2": {"frame":{"x":0,"y":0,"w":96,"h":80},"anchor":{"x":48,"y":72}},
    "mill_construction_3": {"frame":{"x":0,"y":0,"w":96,"h":80},"anchor":{"x":48,"y":72}},
    "mill_complete":       {"frame":{"x":0,"y":0,"w":96,"h":80},"anchor":{"x":48,"y":72}},
    "mill_fire":           {"frame":{"x":0,"y":0,"w":96,"h":80},"anchor":{"x":48,"y":72}},

    "farm_foundation":     {"frame":{"x":0,"y":0,"w":96,"h":80},"anchor":{"x":48,"y":72}},
    "farm_construction_1": {"frame":{"x":0,"y":0,"w":96,"h":80},"anchor":{"x":48,"y":72}},
    "farm_construction_2": {"frame":{"x":0,"y":0,"w":96,"h":80},"anchor":{"x":48,"y":72}},
    "farm_construction_3": {"frame":{"x":0,"y":0,"w":96,"h":80},"anchor":{"x":48,"y":72}},
    "farm_complete":       {"frame":{"x":0,"y":0,"w":96,"h":80},"anchor":{"x":48,"y":72}},
    "farm_fire":           {"frame":{"x":0,"y":0,"w":96,"h":80},"anchor":{"x":48,"y":72}},

    "palisade_wall_foundation":     {"frame":{"x":0,"y":0,"w":64,"h":56},"anchor":{"x":32,"y":48}},
    "palisade_wall_construction_1": {"frame":{"x":0,"y":0,"w":64,"h":56},"anchor":{"x":32,"y":48}},
    "palisade_wall_construction_2": {"frame":{"x":0,"y":0,"w":64,"h":56},"anchor":{"x":32,"y":48}},
    "palisade_wall_construction_3": {"frame":{"x":0,"y":0,"w":64,"h":56},"anchor":{"x":32,"y":48}},
    "palisade_wall_complete":       {"frame":{"x":0,"y":0,"w":64,"h":56},"anchor":{"x":32,"y":48}},
    "palisade_wall_fire":           {"frame":{"x":0,"y":0,"w":64,"h":56},"anchor":{"x":32,"y":48}},

    "stone_wall_foundation":     {"frame":{"x":0,"y":0,"w":64,"h":56},"anchor":{"x":32,"y":48}},
    "stone_wall_construction_1": {"frame":{"x":0,"y":0,"w":64,"h":56},"anchor":{"x":32,"y":48}},
    "stone_wall_construction_2": {"frame":{"x":0,"y":0,"w":64,"h":56},"anchor":{"x":32,"y":48}},
    "stone_wall_construction_3": {"frame":{"x":0,"y":0,"w":64,"h":56},"anchor":{"x":32,"y":48}},
    "stone_wall_complete":       {"frame":{"x":0,"y":0,"w":64,"h":56},"anchor":{"x":32,"y":48}},
    "stone_wall_fire":           {"frame":{"x":0,"y":0,"w":64,"h":56},"anchor":{"x":32,"y":48}},

    "fortified_wall_foundation":     {"frame":{"x":0,"y":0,"w":64,"h":56},"anchor":{"x":32,"y":48}},
    "fortified_wall_construction_1": {"frame":{"x":0,"y":0,"w":64,"h":56},"anchor":{"x":32,"y":48}},
    "fortified_wall_construction_2": {"frame":{"x":0,"y":0,"w":64,"h":56},"anchor":{"x":32,"y":48}},
    "fortified_wall_construction_3": {"frame":{"x":0,"y":0,"w":64,"h":56},"anchor":{"x":32,"y":48}},
    "fortified_wall_complete":       {"frame":{"x":0,"y":0,"w":64,"h":56},"anchor":{"x":32,"y":48}},
    "fortified_wall_fire":           {"frame":{"x":0,"y":0,"w":64,"h":56},"anchor":{"x":32,"y":48}},

    "watch_tower_foundation":     {"frame":{"x":0,"y":0,"w":64,"h":80},"anchor":{"x":32,"y":72}},
    "watch_tower_construction_1": {"frame":{"x":0,"y":0,"w":64,"h":80},"anchor":{"x":32,"y":72}},
    "watch_tower_construction_2": {"frame":{"x":0,"y":0,"w":64,"h":80},"anchor":{"x":32,"y":72}},
    "watch_tower_construction_3": {"frame":{"x":0,"y":0,"w":64,"h":80},"anchor":{"x":32,"y":72}},
    "watch_tower_complete":       {"frame":{"x":0,"y":0,"w":64,"h":80},"anchor":{"x":32,"y":72}},
    "watch_tower_fire":           {"frame":{"x":0,"y":0,"w":64,"h":80},"anchor":{"x":32,"y":72}},

    "guard_tower_foundation":     {"frame":{"x":0,"y":0,"w":64,"h":80},"anchor":{"x":32,"y":72}},
    "guard_tower_construction_1": {"frame":{"x":0,"y":0,"w":64,"h":80},"anchor":{"x":32,"y":72}},
    "guard_tower_construction_2": {"frame":{"x":0,"y":0,"w":64,"h":80},"anchor":{"x":32,"y":72}},
    "guard_tower_construction_3": {"frame":{"x":0,"y":0,"w":64,"h":80},"anchor":{"x":32,"y":72}},
    "guard_tower_complete":       {"frame":{"x":0,"y":0,"w":64,"h":80},"anchor":{"x":32,"y":72}},
    "guard_tower_fire":           {"frame":{"x":0,"y":0,"w":64,"h":80},"anchor":{"x":32,"y":72}},

    "keep_foundation":     {"frame":{"x":0,"y":0,"w":64,"h":80},"anchor":{"x":32,"y":72}},
    "keep_construction_1": {"frame":{"x":0,"y":0,"w":64,"h":80},"anchor":{"x":32,"y":72}},
    "keep_construction_2": {"frame":{"x":0,"y":0,"w":64,"h":80},"anchor":{"x":32,"y":72}},
    "keep_construction_3": {"frame":{"x":0,"y":0,"w":64,"h":80},"anchor":{"x":32,"y":72}},
    "keep_complete":       {"frame":{"x":0,"y":0,"w":64,"h":80},"anchor":{"x":32,"y":72}},
    "keep_fire":           {"frame":{"x":0,"y":0,"w":64,"h":80},"anchor":{"x":32,"y":72}},

    "bombard_tower_foundation":     {"frame":{"x":0,"y":0,"w":64,"h":80},"anchor":{"x":32,"y":72}},
    "bombard_tower_construction_1": {"frame":{"x":0,"y":0,"w":64,"h":80},"anchor":{"x":32,"y":72}},
    "bombard_tower_construction_2": {"frame":{"x":0,"y":0,"w":64,"h":80},"anchor":{"x":32,"y":72}},
    "bombard_tower_construction_3": {"frame":{"x":0,"y":0,"w":64,"h":80},"anchor":{"x":32,"y":72}},
    "bombard_tower_complete":       {"frame":{"x":0,"y":0,"w":64,"h":80},"anchor":{"x":32,"y":72}},
    "bombard_tower_fire":           {"frame":{"x":0,"y":0,"w":64,"h":80},"anchor":{"x":32,"y":72}}
  },
  "animations": {}
}
